{
  "type" : "FeatureCollection",
  "features" : [ {
    "type" : "Feature",
    "geometry" : {
      "type" : "Point",
      "coordinates" : [ -71.1114458017, 42.3754311174 ]
    },
    "properties" : {
      "type" : "place",
      "startTime" : "20140126T214128-0500",
      "endTime" : "20140127T181533-0500",
      "place" : {
        "id" : 9869005,
        "name" : "Home",
        "type" : "home",
        "location" : {
          "lat" : 42.3754311174,
          "lon" : -71.1114458017
        }
      },
      "activities" : [ {
        "activity" : "walking",
        "group" : "walking",
        "manual" : false,
        "startTime" : "20140126T224418-0500",
        "endTime" : "20140126T224448-0500",
        "duration" : 30.0,
        "distance" : 10.0,
        "steps" : 20,
        "calories" : 1
      } ],
      "lastUpdate" : "20140807T114103Z",
      "date" : "20140126"
    }
  } ]
}