{
  "type" : "FeatureCollection",
  "features" : [ {
    "type" : "Feature",
    "geometry" : {
      "type" : "Point",
      "coordinates" : [ -71.1114458017, 42.3754311174 ]
    },
    "properties" : {
      "type" : "place",
      "startTime" : "20140818T223930-0500",
      "endTime" : "20140819T055540-0500",
      "place" : {
        "id" : 9869005,
        "name" : "Home",
        "type" : "home",
        "location" : {
          "lat" : 42.3754311174,
          "lon" : -71.1114458017
        }
      },
      "lastUpdate" : "20140819T120544Z",
      "date" : "20140819"
    }
  }, {
    "type" : "Feature",
    "geometry" : {
      "type" : "Point",
      "coordinates" : [ -71.12210915179602, 42.36578780710847 ]
    },
    "properties" : {
      "type" : "place",
      "startTime" : "20140819T062619-0500",
      "endTime" : "20140819T105239-0500",
      "place" : {
        "id" : 84119446,
        "name" : "Aldrich Hall",
        "type" : "foursquare",
        "foursquareId" : "4ac64359f964a5206eb320e3",
        "foursquareCategoryIds" : [ "4bf58dd8d48988d198941735" ],
        "location" : {
          "lat" : 42.36578780710847,
          "lon" : -71.12210915179602
        }
      },
      "lastUpdate" : "20140821T105057Z",
      "date" : "20140819"
    }
  }, {
    "type" : "Feature",
    "geometry" : {
      "type" : "Point",
      "coordinates" : [ -71.1114458017, 42.3754311174 ]
    },
    "properties" : {
      "type" : "place",
      "startTime" : "20140819T112110-0500",
      "endTime" : "20140819T132753-0500",
      "place" : {
        "id" : 9869005,
        "name" : "Home",
        "type" : "home",
        "location" : {
          "lat" : 42.3754311174,
          "lon" : -71.1114458017
        }
      },
      "lastUpdate" : "20140819T195242Z",
      "date" : "20140819"
    }
  }, {
    "type" : "Feature",
    "geometry" : {
      "type" : "Point",
      "coordinates" : [ -71.12218458495514, 42.36522543920124 ]
    },
    "properties" : {
      "type" : "place",
      "startTime" : "20140819T135535-0500",
      "endTime" : "20140819T202923-0500",
      "place" : {
        "id" : 10115332,
        "name" : "Spangler Center",
        "type" : "foursquare",
        "foursquareId" : "4aeee0b0f964a52081d421e3",
        "foursquareCategoryIds" : [ "4bf58dd8d48988d1ab941735" ],
        "location" : {
          "lat" : 42.36522543920124,
          "lon" : -71.12218458495514
        }
      },
      "lastUpdate" : "20141129T021506Z",
      "date" : "20140819"
    }
  }, {
    "type" : "Feature",
    "geometry" : {
      "type" : "Point",
      "coordinates" : [ -71.12407621183526, 42.36403242532342 ]
    },
    "properties" : {
      "type" : "place",
      "startTime" : "20140819T203507-0500",
      "endTime" : "20140819T215952-0500",
      "place" : {
        "id" : 11237847,
        "name" : "Harvard Innovation Lab",
        "type" : "foursquare",
        "foursquareId" : "4e5d4676ae60839ea2e29e64",
        "foursquareCategoryIds" : [ "4bf58dd8d48988d19f941735" ],
        "location" : {
          "lat" : 42.36403242532342,
          "lon" : -71.12407621183526
        }
      },
      "lastUpdate" : "20141129T021229Z",
      "date" : "20140819"
    }
  }, {
    "type" : "Feature",
    "geometry" : {
      "type" : "Point",
      "coordinates" : [ -71.1161356011, 42.3644780953 ]
    },
    "properties" : {
      "type" : "place",
      "startTime" : "20140819T221046-0500",
      "endTime" : "20140819T221302-0500",
      "place" : {
        "id" : 84438847,
        "type" : "unknown",
        "location" : {
          "lat" : 42.3644780953,
          "lon" : -71.1161356011
        }
      },
      "lastUpdate" : "20140820T115447Z",
      "date" : "20140819"
    }
  }, {
    "type" : "Feature",
    "geometry" : {
      "type" : "Point",
      "coordinates" : [ -71.1139945613, 42.3645380273 ]
    },
    "properties" : {
      "type" : "place",
      "startTime" : "20140819T221539-0500",
      "endTime" : "20140819T222434-0500",
      "place" : {
        "id" : 84438848,
        "type" : "unknown",
        "location" : {
          "lat" : 42.3645380273,
          "lon" : -71.1139945613
        }
      },
      "lastUpdate" : "20140820T115447Z",
      "date" : "20140819"
    }
  }, {
    "type" : "Feature",
    "geometry" : {
      "type" : "Point",
      "coordinates" : [ -71.1114458017, 42.3754311174 ]
    },
    "properties" : {
      "type" : "place",
      "startTime" : "20140819T224146-0500",
      "endTime" : "20140820T065158-0500",
      "place" : {
        "id" : 9869005,
        "name" : "Home",
        "type" : "home",
        "location" : {
          "lat" : 42.3754311174,
          "lon" : -71.1114458017
        }
      },
      "lastUpdate" : "20140820T145654Z",
      "date" : "20140819"
    }
  } ]
}