{
  "type" : "FeatureCollection",
  "features" : [ {
    "type" : "Feature",
    "geometry" : {
      "type" : "Point",
      "coordinates" : [ -71.1114458017, 42.3754311174 ]
    },
    "properties" : {
      "type" : "place",
      "startTime" : "20140602T185118-0400",
      "endTime" : "20140603T093200-0400",
      "place" : {
        "id" : 9869005,
        "name" : "Home",
        "type" : "home",
        "location" : {
          "lat" : 42.3754311174,
          "lon" : -71.1114458017
        }
      },
      "lastUpdate" : "20140807T114103Z",
      "date" : "20140603"
    }
  }, {
    "type" : "Feature",
    "geometry" : {
      "type" : "Point",
      "coordinates" : [ -71.11295, 42.373886 ]
    },
    "properties" : {
      "type" : "place",
      "startTime" : "20140603T093715-0400",
      "endTime" : "20140603T094140-0400",
      "place" : {
        "id" : 51797004,
        "name" : "Starbucks",
        "type" : "foursquare",
        "foursquareId" : "4a5a3eb5f964a520f9b91fe3",
        "foursquareCategoryIds" : [ "4bf58dd8d48988d1e0931735" ],
        "location" : {
          "lat" : 42.373886,
          "lon" : -71.11295
        }
      },
      "lastUpdate" : "20140830T030153Z",
      "date" : "20140603"
    }
  }, {
    "type" : "Feature",
    "geometry" : {
      "type" : "Point",
      "coordinates" : [ -71.117205, 42.378716 ]
    },
    "properties" : {
      "type" : "place",
      "startTime" : "20140603T095216-0400",
      "endTime" : "20140603T121248-0400",
      "place" : {
        "id" : 10149993,
        "name" : "Proximate",
        "type" : "foursquare",
        "foursquareId" : "51c8c0d1498e5d4d09a48362",
        "foursquareCategoryIds" : [ "4bf58dd8d48988d125941735" ],
        "location" : {
          "lat" : 42.378716,
          "lon" : -71.117205
        }
      },
      "lastUpdate" : "20140813T203053Z",
      "date" : "20140603"
    }
  }, {
    "type" : "Feature",
    "geometry" : {
      "type" : "Point",
      "coordinates" : [ -71.1114458017, 42.3754311174 ]
    },
    "properties" : {
      "type" : "place",
      "startTime" : "20140603T122257-0400",
      "endTime" : "20140603T133531-0400",
      "place" : {
        "id" : 9869005,
        "name" : "Home",
        "type" : "home",
        "location" : {
          "lat" : 42.3754311174,
          "lon" : -71.1114458017
        }
      },
      "lastUpdate" : "20140807T114103Z",
      "date" : "20140603"
    }
  }, {
    "type" : "Feature",
    "geometry" : {
      "type" : "Point",
      "coordinates" : [ -71.117205, 42.378716 ]
    },
    "properties" : {
      "type" : "place",
      "startTime" : "20140603T134858-0400",
      "endTime" : "20140603T154202-0400",
      "place" : {
        "id" : 10149993,
        "name" : "Proximate",
        "type" : "foursquare",
        "foursquareId" : "51c8c0d1498e5d4d09a48362",
        "foursquareCategoryIds" : [ "4bf58dd8d48988d125941735" ],
        "location" : {
          "lat" : 42.378716,
          "lon" : -71.117205
        }
      },
      "lastUpdate" : "20140813T203053Z",
      "date" : "20140603"
    }
  }, {
    "type" : "Feature",
    "geometry" : {
      "type" : "Point",
      "coordinates" : [ -71.1114458017, 42.3754311174 ]
    },
    "properties" : {
      "type" : "place",
      "startTime" : "20140603T155508-0400",
      "endTime" : "20140603T161433-0400",
      "place" : {
        "id" : 9869005,
        "name" : "Home",
        "type" : "home",
        "location" : {
          "lat" : 42.3754311174,
          "lon" : -71.1114458017
        }
      },
      "lastUpdate" : "20140807T114103Z",
      "date" : "20140603"
    }
  }, {
    "type" : "Feature",
    "geometry" : {
      "type" : "Point",
      "coordinates" : [ -71.117205, 42.378716 ]
    },
    "properties" : {
      "type" : "place",
      "startTime" : "20140603T162446-0400",
      "endTime" : "20140603T194132-0400",
      "place" : {
        "id" : 10149993,
        "name" : "Proximate",
        "type" : "foursquare",
        "foursquareId" : "51c8c0d1498e5d4d09a48362",
        "foursquareCategoryIds" : [ "4bf58dd8d48988d125941735" ],
        "location" : {
          "lat" : 42.378716,
          "lon" : -71.117205
        }
      },
      "lastUpdate" : "20140813T203053Z",
      "date" : "20140603"
    }
  }, {
    "type" : "Feature",
    "geometry" : {
      "type" : "Point",
      "coordinates" : [ -71.1114458017, 42.3754311174 ]
    },
    "properties" : {
      "type" : "place",
      "startTime" : "20140603T195354-0400",
      "endTime" : "20140604T092258-0400",
      "place" : {
        "id" : 9869005,
        "name" : "Home",
        "type" : "home",
        "location" : {
          "lat" : 42.3754311174,
          "lon" : -71.1114458017
        }
      },
      "lastUpdate" : "20140807T114103Z",
      "date" : "20140603"
    }
  } ]
}