{
  "type" : "FeatureCollection",
  "features" : [ {
    "type" : "Feature",
    "geometry" : {
      "type" : "Point",
      "coordinates" : [ -71.1114458017, 42.3754311174 ]
    },
    "properties" : {
      "type" : "place",
      "startTime" : "20140913T163806-0400",
      "endTime" : "20140914T130342-0400",
      "place" : {
        "id" : 9869005,
        "name" : "Home",
        "type" : "home",
        "location" : {
          "lat" : 42.3754311174,
          "lon" : -71.1114458017
        }
      },
      "lastUpdate" : "20140914T181623Z",
      "date" : "20140914"
    }
  }, {
    "type" : "Feature",
    "geometry" : {
      "type" : "Point",
      "coordinates" : [ -71.119043, 42.373776 ]
    },
    "properties" : {
      "type" : "place",
      "startTime" : "20140914T131826-0400",
      "endTime" : "20140914T132440-0400",
      "place" : {
        "id" : 94226569,
        "name" : "Staples",
        "type" : "foursquare",
        "foursquareId" : "4b1e88eaf964a520321b24e3",
        "foursquareCategoryIds" : [ "4bf58dd8d48988d121951735" ],
        "location" : {
          "lat" : 42.373776,
          "lon" : -71.119043
        }
      },
      "lastUpdate" : "20141016T015158Z",
      "date" : "20140914"
    }
  }, {
    "type" : "Feature",
    "geometry" : {
      "type" : "Point",
      "coordinates" : [ -71.11655026913272, 42.3717166982379 ]
    },
    "properties" : {
      "type" : "place",
      "startTime" : "20140914T133052-0400",
      "endTime" : "20140914T133319-0400",
      "place" : {
        "id" : 94226617,
        "name" : "Adams House",
        "type" : "foursquare",
        "foursquareId" : "4b5e4514f964a520f28629e3",
        "foursquareCategoryIds" : [ "4bf58dd8d48988d1a3941735" ],
        "location" : {
          "lat" : 42.3717166982379,
          "lon" : -71.11655026913272
        }
      },
      "lastUpdate" : "20140917T023934Z",
      "date" : "20140914"
    }
  }, {
    "type" : "Feature",
    "geometry" : {
      "type" : "Point",
      "coordinates" : [ -71.1114458017, 42.3754311174 ]
    },
    "properties" : {
      "type" : "place",
      "startTime" : "20140914T134521-0400",
      "endTime" : "20140915T072606-0400",
      "place" : {
        "id" : 9869005,
        "name" : "Home",
        "type" : "home",
        "location" : {
          "lat" : 42.3754311174,
          "lon" : -71.1114458017
        }
      },
      "lastUpdate" : "20140915T125411Z",
      "date" : "20140914"
    }
  } ]
}