{
  "type" : "FeatureCollection",
  "features" : [ {
    "type" : "Feature",
    "geometry" : {
      "type" : "Point",
      "coordinates" : [ -77.07371486668141, 38.92592014653639 ]
    },
    "properties" : {
      "type" : "place",
      "startTime" : "20140117T192942-0600",
      "endTime" : "20140118T130236-0600",
      "place" : {
        "id" : 20154436,
        "name" : "2440 39th St NW",
        "type" : "foursquare",
        "foursquareId" : "520fad0811d2245250b13cd1",
        "location" : {
          "lat" : 38.92592014653639,
          "lon" : -77.07371486668141
        }
      },
      "lastUpdate" : "20140118T232955Z",
      "date" : "20140118"
    }
  }, {
    "type" : "Feature",
    "geometry" : {
      "type" : "Point",
      "coordinates" : [ -76.92824363708496, 39.02135091580463 ]
    },
    "properties" : {
      "type" : "place",
      "startTime" : "20140118T134706-0600",
      "endTime" : "20140118T172923-0600",
      "place" : {
        "id" : 20235988,
        "name" : "IKEA",
        "type" : "foursquare",
        "foursquareId" : "4b1a8fb7f964a52058ec23e3",
        "location" : {
          "lat" : 39.02135091580463,
          "lon" : -76.92824363708496
        }
      },
      "lastUpdate" : "20140119T012142Z",
      "date" : "20140118"
    }
  }, {
    "type" : "Feature",
    "geometry" : {
      "type" : "Point",
      "coordinates" : [ -77.07371486668141, 38.92592014653639 ]
    },
    "properties" : {
      "type" : "place",
      "startTime" : "20140118T180511-0600",
      "endTime" : "20140119T131816-0600",
      "place" : {
        "id" : 20384746,
        "name" : "2440 39th St NW",
        "type" : "foursquare",
        "foursquareId" : "520fad0811d2245250b13cd1",
        "location" : {
          "lat" : 38.92592014653639,
          "lon" : -77.07371486668141
        }
      },
      "lastUpdate" : "20140119T210721Z",
      "date" : "20140118"
    }
  } ]
}