{
  "type" : "FeatureCollection",
  "features" : [ {
    "type" : "Feature",
    "geometry" : {
      "type" : "Point",
      "coordinates" : [ -71.08726143836975, 42.36365726858562 ]
    },
    "properties" : {
      "type" : "place",
      "startTime" : "20140130T202817-0500",
      "endTime" : "20140131T005340-0500",
      "place" : {
        "id" : 22585452,
        "name" : "Meadhall",
        "type" : "foursquare",
        "foursquareId" : "4db81694f7b15ca52ce24788",
        "location" : {
          "lat" : 42.36365726858562,
          "lon" : -71.08726143836975
        }
      },
      "lastUpdate" : "20140131T070657Z",
      "date" : "20140131"
    }
  }, {
    "type" : "Feature",
    "geometry" : {
      "type" : "Point",
      "coordinates" : [ -71.1114458017, 42.3754311174 ]
    },
    "properties" : {
      "type" : "place",
      "startTime" : "20140131T005924-0500",
      "endTime" : "20140131T125437-0500",
      "place" : {
        "id" : 9869005,
        "name" : "Home",
        "type" : "home",
        "location" : {
          "lat" : 42.3754311174,
          "lon" : -71.1114458017
        }
      },
      "lastUpdate" : "20140321T123025Z",
      "date" : "20140131"
    }
  }, {
    "type" : "Feature",
    "geometry" : {
      "type" : "Point",
      "coordinates" : [ -71.117205, 42.378716 ]
    },
    "properties" : {
      "type" : "place",
      "startTime" : "20140131T130240-0500",
      "endTime" : "20140131T153406-0500",
      "place" : {
        "id" : 10149993,
        "name" : "Proximate",
        "type" : "foursquare",
        "foursquareId" : "51c8c0d1498e5d4d09a48362",
        "foursquareCategoryIds" : [ "4bf58dd8d48988d125941735" ],
        "location" : {
          "lat" : 42.378716,
          "lon" : -71.117205
        }
      },
      "lastUpdate" : "20140206T183044Z",
      "date" : "20140131"
    }
  }, {
    "type" : "Feature",
    "geometry" : {
      "type" : "Point",
      "coordinates" : [ -71.1241282979, 42.3771299622 ]
    },
    "properties" : {
      "type" : "place",
      "startTime" : "20140131T155521-0500",
      "endTime" : "20140131T173454-0500",
      "place" : {
        "id" : 22762920,
        "type" : "unknown",
        "location" : {
          "lat" : 42.3771299622,
          "lon" : -71.1241282979
        }
      },
      "lastUpdate" : "20140201T005652Z",
      "date" : "20140131"
    }
  }, {
    "type" : "Feature",
    "geometry" : {
      "type" : "Point",
      "coordinates" : [ -71.1114458017, 42.3754311174 ]
    },
    "properties" : {
      "type" : "place",
      "startTime" : "20140131T175338-0500",
      "endTime" : "20140131T181949-0500",
      "place" : {
        "id" : 9869005,
        "name" : "Home",
        "type" : "home",
        "location" : {
          "lat" : 42.3754311174,
          "lon" : -71.1114458017
        }
      },
      "lastUpdate" : "20140321T123025Z",
      "date" : "20140131"
    }
  }, {
    "type" : "Feature",
    "geometry" : {
      "type" : "Point",
      "coordinates" : [ -71.1155814053, 42.3722049374 ]
    },
    "properties" : {
      "type" : "place",
      "startTime" : "20140131T182922-0500",
      "endTime" : "20140131T194712-0500",
      "place" : {
        "id" : 22762925,
        "type" : "unknown",
        "location" : {
          "lat" : 42.3722049374,
          "lon" : -71.1155814053
        }
      },
      "lastUpdate" : "20140201T033113Z",
      "date" : "20140131"
    }
  }, {
    "type" : "Feature",
    "geometry" : {
      "type" : "Point",
      "coordinates" : [ -71.1114458017, 42.3754311174 ]
    },
    "properties" : {
      "type" : "place",
      "startTime" : "20140131T195547-0500",
      "endTime" : "20140201T124717-0500",
      "place" : {
        "id" : 9869005,
        "name" : "Home",
        "type" : "home",
        "location" : {
          "lat" : 42.3754311174,
          "lon" : -71.1114458017
        }
      },
      "lastUpdate" : "20140321T123025Z",
      "date" : "20140131"
    }
  } ]
}