{
  "type" : "FeatureCollection",
  "features" : [ {
    "type" : "Feature",
    "geometry" : {
      "type" : "Point",
      "coordinates" : [ -77.00518563613092, 38.89803898801969 ]
    },
    "properties" : {
      "type" : "place",
      "startTime" : "20140304T095037-0500",
      "endTime" : "20140304T101530-0500",
      "place" : {
        "id" : 28903562,
        "name" : "Union Station | Gate K",
        "type" : "foursquare",
        "foursquareId" : "4fa9356ee4b08cc7d9bbddb5",
        "foursquareCategoryIds" : [ "4f4531504b9074f6e4fb0102" ],
        "location" : {
          "lat" : 38.89803898801969,
          "lon" : -77.00518563613092
        }
      },
      "lastUpdate" : "20140305T012705Z",
      "date" : "20140304"
    }
  }, {
    "type" : "Feature",
    "geometry" : {
      "type" : "Point",
      "coordinates" : [ -71.1114458017, 42.3754311174 ]
    },
    "properties" : {
      "type" : "place",
      "startTime" : "20140304T190732-0500",
      "endTime" : "20140305T091935-0500",
      "place" : {
        "id" : 9869005,
        "name" : "Home",
        "type" : "home",
        "location" : {
          "lat" : 42.3754311174,
          "lon" : -71.1114458017
        }
      },
      "lastUpdate" : "20140321T123025Z",
      "date" : "20140304"
    }
  } ]
}