{
  "type" : "FeatureCollection",
  "features" : [ {
    "type" : "Feature",
    "geometry" : {
      "type" : "Point",
      "coordinates" : [ -71.1114458017, 42.3754311174 ]
    },
    "properties" : {
      "type" : "place",
      "startTime" : "20140130T235924-0600",
      "endTime" : "20140131T115437-0600",
      "place" : {
        "id" : 9869005,
        "name" : "Home",
        "type" : "home",
        "location" : {
          "lat" : 42.3754311174,
          "lon" : -71.1114458017
        }
      },
      "lastUpdate" : "20140321T123025Z",
      "date" : "20140131"
    }
  }, {
    "type" : "Feature",
    "geometry" : {
      "type" : "Point",
      "coordinates" : [ -71.117205, 42.378716 ]
    },
    "properties" : {
      "type" : "place",
      "startTime" : "20140131T120240-0600",
      "endTime" : "20140131T143406-0600",
      "place" : {
        "id" : 10149993,
        "name" : "Proximate",
        "type" : "foursquare",
        "foursquareId" : "51c8c0d1498e5d4d09a48362",
        "foursquareCategoryIds" : [ "4bf58dd8d48988d125941735" ],
        "location" : {
          "lat" : 42.378716,
          "lon" : -71.117205
        }
      },
      "lastUpdate" : "20140612T223544Z",
      "date" : "20140131"
    }
  }, {
    "type" : "Feature",
    "geometry" : {
      "type" : "Point",
      "coordinates" : [ -71.1241282979, 42.3771299622 ]
    },
    "properties" : {
      "type" : "place",
      "startTime" : "20140131T145521-0600",
      "endTime" : "20140131T163454-0600",
      "place" : {
        "id" : 22762920,
        "type" : "unknown",
        "location" : {
          "lat" : 42.3771299622,
          "lon" : -71.1241282979
        }
      },
      "lastUpdate" : "20140201T005652Z",
      "date" : "20140131"
    }
  }, {
    "type" : "Feature",
    "geometry" : {
      "type" : "Point",
      "coordinates" : [ -71.1114458017, 42.3754311174 ]
    },
    "properties" : {
      "type" : "place",
      "startTime" : "20140131T165338-0600",
      "endTime" : "20140131T171949-0600",
      "place" : {
        "id" : 9869005,
        "name" : "Home",
        "type" : "home",
        "location" : {
          "lat" : 42.3754311174,
          "lon" : -71.1114458017
        }
      },
      "lastUpdate" : "20140321T123025Z",
      "date" : "20140131"
    }
  }, {
    "type" : "Feature",
    "geometry" : {
      "type" : "Point",
      "coordinates" : [ -71.1155814053, 42.3722049374 ]
    },
    "properties" : {
      "type" : "place",
      "startTime" : "20140131T172922-0600",
      "endTime" : "20140131T184712-0600",
      "place" : {
        "id" : 22762925,
        "type" : "unknown",
        "location" : {
          "lat" : 42.3722049374,
          "lon" : -71.1155814053
        }
      },
      "lastUpdate" : "20140201T033113Z",
      "date" : "20140131"
    }
  }, {
    "type" : "Feature",
    "geometry" : {
      "type" : "Point",
      "coordinates" : [ -71.1114458017, 42.3754311174 ]
    },
    "properties" : {
      "type" : "place",
      "startTime" : "20140131T185547-0600",
      "endTime" : "20140201T114717-0600",
      "place" : {
        "id" : 9869005,
        "name" : "Home",
        "type" : "home",
        "location" : {
          "lat" : 42.3754311174,
          "lon" : -71.1114458017
        }
      },
      "lastUpdate" : "20140321T123025Z",
      "date" : "20140131"
    }
  } ]
}