{
  "type" : "FeatureCollection",
  "features" : [ {
    "type" : "Feature",
    "geometry" : {
      "type" : "Point",
      "coordinates" : [ -71.1114458017, 42.3754311174 ]
    },
    "properties" : {
      "type" : "place",
      "startTime" : "20140224T171428-0600",
      "endTime" : "20140225T095759-0600",
      "place" : {
        "id" : 9869005,
        "name" : "Home",
        "type" : "home",
        "location" : {
          "lat" : 42.3754311174,
          "lon" : -71.1114458017
        }
      },
      "lastUpdate" : "20140807T114103Z",
      "date" : "20140225"
    }
  }, {
    "type" : "Feature",
    "geometry" : {
      "type" : "Point",
      "coordinates" : [ -71.1132681841, 42.37582268 ]
    },
    "properties" : {
      "type" : "place",
      "startTime" : "20140225T100208-0600",
      "endTime" : "20140225T100459-0600",
      "place" : {
        "id" : 27552313,
        "type" : "unknown",
        "location" : {
          "lat" : 42.37582268,
          "lon" : -71.1132681841
        }
      },
      "lastUpdate" : "20140225T174834Z",
      "date" : "20140225"
    }
  }, {
    "type" : "Feature",
    "geometry" : {
      "type" : "Point",
      "coordinates" : [ -71.117205, 42.378716 ]
    },
    "properties" : {
      "type" : "place",
      "startTime" : "20140225T101610-0600",
      "endTime" : "20140225T114711-0600",
      "place" : {
        "id" : 10149993,
        "name" : "Proximate",
        "type" : "foursquare",
        "foursquareId" : "51c8c0d1498e5d4d09a48362",
        "foursquareCategoryIds" : [ "4bf58dd8d48988d125941735" ],
        "location" : {
          "lat" : 42.378716,
          "lon" : -71.117205
        }
      },
      "lastUpdate" : "20140813T203053Z",
      "date" : "20140225"
    }
  }, {
    "type" : "Feature",
    "geometry" : {
      "type" : "Point",
      "coordinates" : [ -71.11866242152347, 42.37890166598297 ]
    },
    "properties" : {
      "type" : "place",
      "startTime" : "20140225T115121-0600",
      "endTime" : "20140225T123701-0600",
      "place" : {
        "id" : 26549346,
        "name" : "Caspersen Student Center",
        "type" : "foursquare",
        "foursquareId" : "4e790134b0fb5d40982b00d0",
        "foursquareCategoryIds" : [ "4bf58dd8d48988d1a1941735" ],
        "location" : {
          "lat" : 42.37890166598297,
          "lon" : -71.11866242152347
        }
      },
      "lastUpdate" : "20140225T195453Z",
      "date" : "20140225"
    }
  }, {
    "type" : "Feature",
    "geometry" : {
      "type" : "Point",
      "coordinates" : [ -71.117205, 42.378716 ]
    },
    "properties" : {
      "type" : "place",
      "startTime" : "20140225T124013-0600",
      "endTime" : "20140225T124330-0600",
      "place" : {
        "id" : 10149993,
        "name" : "Proximate",
        "type" : "foursquare",
        "foursquareId" : "51c8c0d1498e5d4d09a48362",
        "foursquareCategoryIds" : [ "4bf58dd8d48988d125941735" ],
        "location" : {
          "lat" : 42.378716,
          "lon" : -71.117205
        }
      },
      "lastUpdate" : "20140813T203053Z",
      "date" : "20140225"
    }
  }, {
    "type" : "Feature",
    "geometry" : {
      "type" : "Point",
      "coordinates" : [ -71.1114458017, 42.3754311174 ]
    },
    "properties" : {
      "type" : "place",
      "startTime" : "20140225T125628-0600",
      "endTime" : "20140227T072209-0600",
      "place" : {
        "id" : 9869005,
        "name" : "Home",
        "type" : "home",
        "location" : {
          "lat" : 42.3754311174,
          "lon" : -71.1114458017
        }
      },
      "lastUpdate" : "20140807T114103Z",
      "date" : "20140225"
    }
  } ]
}