{
  "type" : "FeatureCollection",
  "features" : [ {
    "type" : "Feature",
    "geometry" : {
      "type" : "Point",
      "coordinates" : [ -71.1114458017, 42.3754311174 ]
    },
    "properties" : {
      "type" : "place",
      "startTime" : "20131209T232134-0600",
      "endTime" : "20131210T185615-0600",
      "place" : {
        "id" : 9869005,
        "name" : "Home",
        "type" : "home",
        "location" : {
          "lat" : 42.3754311174,
          "lon" : -71.1114458017
        }
      },
      "lastUpdate" : "20140321T123025Z",
      "date" : "20131210"
    }
  }, {
    "type" : "Feature",
    "geometry" : {
      "type" : "Point",
      "coordinates" : [ -71.11300484548056, 42.37405171427381 ]
    },
    "properties" : {
      "type" : "place",
      "startTime" : "20131210T190201-0600",
      "endTime" : "20131210T191524-0600",
      "place" : {
        "id" : 9869004,
        "name" : "Broadway Marketplace",
        "type" : "foursquare",
        "foursquareId" : "4a661612f964a520ffc71fe3",
        "foursquareCategoryIds" : [ "4bf58dd8d48988d118951735", "4bf58dd8d48988d1f5941735" ],
        "location" : {
          "lat" : 42.37405171427381,
          "lon" : -71.11300484548056
        }
      },
      "lastUpdate" : "20140601T234927Z",
      "date" : "20131210"
    }
  }, {
    "type" : "Feature",
    "geometry" : {
      "type" : "Point",
      "coordinates" : [ -71.1114458017, 42.3754311174 ]
    },
    "properties" : {
      "type" : "place",
      "startTime" : "20131210T192250-0600",
      "endTime" : "20131210T222342-0600",
      "place" : {
        "id" : 9869005,
        "name" : "Home",
        "type" : "home",
        "location" : {
          "lat" : 42.3754311174,
          "lon" : -71.1114458017
        }
      },
      "lastUpdate" : "20140321T123025Z",
      "date" : "20131210"
    }
  } ]
}