{
  "type" : "FeatureCollection",
  "features" : [ {
    "type" : "Feature",
    "geometry" : {
      "type" : "Point",
      "coordinates" : [ -71.1114458017, 42.3754311174 ]
    },
    "properties" : {
      "type" : "place",
      "startTime" : "20131207T145745-0600",
      "endTime" : "20131208T102701-0600",
      "place" : {
        "id" : 9869005,
        "name" : "Home",
        "type" : "home",
        "location" : {
          "lat" : 42.3754311174,
          "lon" : -71.1114458017
        }
      },
      "lastUpdate" : "20140807T114103Z",
      "date" : "20131208"
    }
  }, {
    "type" : "Feature",
    "geometry" : {
      "type" : "Point",
      "coordinates" : [ -71.1043402003, 42.3704831417 ]
    },
    "properties" : {
      "type" : "place",
      "startTime" : "20131208T103642-0600",
      "endTime" : "20131208T112749-0600",
      "place" : {
        "id" : 10935027,
        "type" : "unknown",
        "location" : {
          "lat" : 42.3704831417,
          "lon" : -71.1043402003
        }
      },
      "lastUpdate" : "20131208T193418Z",
      "date" : "20131208"
    }
  }, {
    "type" : "Feature",
    "geometry" : {
      "type" : "Point",
      "coordinates" : [ -71.1114458017, 42.3754311174 ]
    },
    "properties" : {
      "type" : "place",
      "startTime" : "20131208T114831-0600",
      "endTime" : "20131208T120636-0600",
      "place" : {
        "id" : 9869005,
        "name" : "Home",
        "type" : "home",
        "location" : {
          "lat" : 42.3754311174,
          "lon" : -71.1114458017
        }
      },
      "lastUpdate" : "20140807T114103Z",
      "date" : "20131208"
    }
  }, {
    "type" : "Feature",
    "geometry" : {
      "type" : "Point",
      "coordinates" : [ -71.1114458017, 42.3754311174 ]
    },
    "properties" : {
      "type" : "place",
      "startTime" : "20131208T121528-0600",
      "endTime" : "20131209T065715-0600",
      "place" : {
        "id" : 9869005,
        "name" : "Home",
        "type" : "home",
        "location" : {
          "lat" : 42.3754311174,
          "lon" : -71.1114458017
        }
      },
      "lastUpdate" : "20140807T114103Z",
      "date" : "20131208"
    }
  } ]
}