{
  "type" : "FeatureCollection",
  "features" : [ {
    "type" : "Feature",
    "geometry" : {
      "type" : "Point",
      "coordinates" : [ -71.1114458017, 42.3754311174 ]
    },
    "properties" : {
      "type" : "place",
      "startTime" : "20140222T222756-0600",
      "endTime" : "20140223T112323-0600",
      "place" : {
        "id" : 9869005,
        "name" : "Home",
        "type" : "home",
        "location" : {
          "lat" : 42.3754311174,
          "lon" : -71.1114458017
        }
      },
      "lastUpdate" : "20140807T114103Z",
      "date" : "20140223"
    }
  }, {
    "type" : "Feature",
    "geometry" : {
      "type" : "Point",
      "coordinates" : [ -71.117205, 42.378716 ]
    },
    "properties" : {
      "type" : "place",
      "startTime" : "20140223T113407-0600",
      "endTime" : "20140223T162842-0600",
      "place" : {
        "id" : 10149993,
        "name" : "Proximate",
        "type" : "foursquare",
        "foursquareId" : "51c8c0d1498e5d4d09a48362",
        "foursquareCategoryIds" : [ "4bf58dd8d48988d125941735" ],
        "location" : {
          "lat" : 42.378716,
          "lon" : -71.117205
        }
      },
      "lastUpdate" : "20140813T203053Z",
      "date" : "20140223"
    }
  }, {
    "type" : "Feature",
    "geometry" : {
      "type" : "Point",
      "coordinates" : [ -71.1114458017, 42.3754311174 ]
    },
    "properties" : {
      "type" : "place",
      "startTime" : "20140223T164119-0600",
      "endTime" : "20140224T074457-0600",
      "place" : {
        "id" : 9869005,
        "name" : "Home",
        "type" : "home",
        "location" : {
          "lat" : 42.3754311174,
          "lon" : -71.1114458017
        }
      },
      "lastUpdate" : "20140807T114103Z",
      "date" : "20140223"
    }
  } ]
}