{
  "type" : "FeatureCollection",
  "features" : [ {
    "type" : "Feature",
    "geometry" : {
      "type" : "Point",
      "coordinates" : [ -77.07371486668141, 38.92592014653639 ]
    },
    "properties" : {
      "type" : "place",
      "startTime" : "20140120T204529-0500",
      "endTime" : "20140121T131216-0500",
      "place" : {
        "id" : 20744767,
        "name" : "2440 39th St NW",
        "type" : "foursquare",
        "foursquareId" : "520fad0811d2245250b13cd1",
        "location" : {
          "lat" : 38.92592014653639,
          "lon" : -77.07371486668141
        }
      },
      "lastUpdate" : "20140121T192049Z",
      "date" : "20140121"
    }
  }, {
    "type" : "Feature",
    "geometry" : {
      "type" : "Point",
      "coordinates" : [ -77.071804, 38.920938 ]
    },
    "properties" : {
      "type" : "place",
      "startTime" : "20140121T132720-0500",
      "endTime" : "20140121T140852-0500",
      "place" : {
        "id" : 12721207,
        "name" : "Whole Foods Market",
        "type" : "foursquare",
        "foursquareId" : "4aad58b8f964a520d25f20e3",
        "foursquareCategoryIds" : [ "4bf58dd8d48988d118951735", "4bf58dd8d48988d1d3941735", "4bf58dd8d48988d16a941735" ],
        "location" : {
          "lat" : 38.920938,
          "lon" : -77.071804
        }
      },
      "lastUpdate" : "20140222T170558Z",
      "date" : "20140121"
    }
  }, {
    "type" : "Feature",
    "geometry" : {
      "type" : "Point",
      "coordinates" : [ -77.07371486668141, 38.92592014653639 ]
    },
    "properties" : {
      "type" : "place",
      "startTime" : "20140121T141835-0500",
      "endTime" : "20140122T162140-0500",
      "place" : {
        "id" : 21541904,
        "name" : "2440 39th St NW",
        "type" : "foursquare",
        "foursquareId" : "520fad0811d2245250b13cd1",
        "location" : {
          "lat" : 38.92592014653639,
          "lon" : -77.07371486668141
        }
      },
      "lastUpdate" : "20140125T150825Z",
      "date" : "20140121"
    }
  } ]
}