{
  "type" : "FeatureCollection",
  "features" : [ {
    "type" : "Feature",
    "geometry" : {
      "type" : "Point",
      "coordinates" : [ -71.1114458017, 42.3754311174 ]
    },
    "properties" : {
      "type" : "place",
      "startTime" : "20140607T205507-0500",
      "endTime" : "20140608T115634-0500",
      "place" : {
        "id" : 9869005,
        "name" : "Home",
        "type" : "home",
        "location" : {
          "lat" : 42.3754311174,
          "lon" : -71.1114458017
        }
      },
      "lastUpdate" : "20140807T114103Z",
      "date" : "20140608"
    }
  }, {
    "type" : "Feature",
    "geometry" : {
      "type" : "Point",
      "coordinates" : [ -71.3302266069, 42.3485322044 ]
    },
    "properties" : {
      "type" : "place",
      "startTime" : "20140608T123257-0500",
      "endTime" : "20140608T174144-0500",
      "place" : {
        "id" : 58695698,
        "name" : "Frankel Home",
        "type" : "home",
        "location" : {
          "lat" : 42.3485322044,
          "lon" : -71.3302266069
        }
      },
      "lastUpdate" : "20140610T121833Z",
      "date" : "20140608"
    }
  }, {
    "type" : "Feature",
    "geometry" : {
      "type" : "Point",
      "coordinates" : [ -71.1114458017, 42.3754311174 ]
    },
    "properties" : {
      "type" : "place",
      "startTime" : "20140608T181003-0500",
      "endTime" : "20140609T210553-0500",
      "place" : {
        "id" : 9869005,
        "name" : "Home",
        "type" : "home",
        "location" : {
          "lat" : 42.3754311174,
          "lon" : -71.1114458017
        }
      },
      "lastUpdate" : "20140807T114103Z",
      "date" : "20140608"
    }
  } ]
}