{
  "type" : "FeatureCollection",
  "features" : [ {
    "type" : "Feature",
    "geometry" : {
      "type" : "Point",
      "coordinates" : [ -71.1114458017, 42.3754311174 ]
    },
    "properties" : {
      "type" : "place",
      "startTime" : "20140517T235421-0500",
      "endTime" : "20140518T095111-0500",
      "place" : {
        "id" : 9869005,
        "name" : "Home",
        "type" : "home",
        "location" : {
          "lat" : 42.3754311174,
          "lon" : -71.1114458017
        }
      },
      "lastUpdate" : "20140518T165530Z",
      "date" : "20140518"
    }
  }, {
    "type" : "Feature",
    "geometry" : {
      "type" : "Point",
      "coordinates" : [ -71.120509, 42.372612 ]
    },
    "properties" : {
      "type" : "place",
      "startTime" : "20140518T100455-0500",
      "endTime" : "20140518T101253-0500",
      "place" : {
        "id" : 51050972,
        "name" : "Peet's Coffee & Tea",
        "type" : "foursquare",
        "foursquareId" : "4a60b9adf964a52014c11fe3",
        "foursquareCategoryIds" : [ "4bf58dd8d48988d1e0931735" ],
        "location" : {
          "lat" : 42.372612,
          "lon" : -71.120509
        }
      },
      "lastUpdate" : "20140518T165652Z",
      "date" : "20140518"
    }
  }, {
    "type" : "Feature",
    "geometry" : {
      "type" : "Point",
      "coordinates" : [ -71.119457, 42.373379 ]
    },
    "properties" : {
      "type" : "place",
      "startTime" : "20140518T101731-0500",
      "endTime" : "20140518T110149-0500",
      "place" : {
        "id" : 30131139,
        "name" : "Tory Row",
        "type" : "foursquare",
        "foursquareId" : "49e79621f964a520cf641fe3",
        "foursquareCategoryIds" : [ "4bf58dd8d48988d14e941735" ],
        "location" : {
          "lat" : 42.373379,
          "lon" : -71.119457
        }
      },
      "lastUpdate" : "20140601T235008Z",
      "date" : "20140518"
    }
  }, {
    "type" : "Feature",
    "geometry" : {
      "type" : "Point",
      "coordinates" : [ -71.1114458017, 42.3754311174 ]
    },
    "properties" : {
      "type" : "place",
      "startTime" : "20140518T112325-0500",
      "endTime" : "20140518T144032-0500",
      "place" : {
        "id" : 9869005,
        "name" : "Home",
        "type" : "home",
        "location" : {
          "lat" : 42.3754311174,
          "lon" : -71.1114458017
        }
      },
      "lastUpdate" : "20140518T202809Z",
      "date" : "20140518"
    }
  }, {
    "type" : "Feature",
    "geometry" : {
      "type" : "Point",
      "coordinates" : [ -71.109389, 42.37488104 ]
    },
    "properties" : {
      "type" : "place",
      "startTime" : "20140518T144339-0500",
      "endTime" : "20140518T152537-0500",
      "place" : {
        "id" : 10293866,
        "name" : "Darwin's Ltd.",
        "type" : "foursquare",
        "foursquareId" : "4a1c900cf964a520507b1fe3",
        "foursquareCategoryIds" : [ "4bf58dd8d48988d1c5941735", "4bf58dd8d48988d143941735" ],
        "location" : {
          "lat" : 42.37488104,
          "lon" : -71.109389
        }
      },
      "lastUpdate" : "20140519T004528Z",
      "date" : "20140518"
    }
  }, {
    "type" : "Feature",
    "geometry" : {
      "type" : "Point",
      "coordinates" : [ -71.1114458017, 42.3754311174 ]
    },
    "properties" : {
      "type" : "place",
      "startTime" : "20140518T152825-0500",
      "endTime" : "20140519T090332-0500",
      "place" : {
        "id" : 9869005,
        "name" : "Home",
        "type" : "home",
        "location" : {
          "lat" : 42.3754311174,
          "lon" : -71.1114458017
        }
      },
      "lastUpdate" : "20140519T172850Z",
      "date" : "20140518"
    }
  } ]
}