{
  "type" : "FeatureCollection",
  "features" : [ {
    "type" : "Feature",
    "geometry" : {
      "type" : "Point",
      "coordinates" : [ -88.311048021, 41.8771070061 ]
    },
    "properties" : {
      "type" : "place",
      "startTime" : "20140327T131359-0500",
      "endTime" : "20140328T141316-0500",
      "place" : {
        "id" : 17698839,
        "name" : "Fitzsimmons Home",
        "type" : "home",
        "location" : {
          "lat" : 41.8771070061,
          "lon" : -88.311048021
        }
      },
      "lastUpdate" : "20140703T042334Z",
      "date" : "20140328"
    }
  }, {
    "type" : "Feature",
    "geometry" : {
      "type" : "Point",
      "coordinates" : [ -88.3417491588, 41.919983156 ]
    },
    "properties" : {
      "type" : "place",
      "startTime" : "20140328T142421-0500",
      "endTime" : "20140328T145401-0500",
      "place" : {
        "id" : 34693339,
        "type" : "unknown",
        "location" : {
          "lat" : 41.919983156,
          "lon" : -88.3417491588
        }
      },
      "lastUpdate" : "20140328T212848Z",
      "date" : "20140328"
    }
  }, {
    "type" : "Feature",
    "geometry" : {
      "type" : "Point",
      "coordinates" : [ -88.311048021, 41.8771070061 ]
    },
    "properties" : {
      "type" : "place",
      "startTime" : "20140328T151000-0500",
      "endTime" : "20140329T154526-0500",
      "place" : {
        "id" : 17698839,
        "name" : "Fitzsimmons Home",
        "type" : "home",
        "location" : {
          "lat" : 41.8771070061,
          "lon" : -88.311048021
        }
      },
      "lastUpdate" : "20140703T042334Z",
      "date" : "20140328"
    }
  } ]
}