{
  "type" : "FeatureCollection",
  "features" : [ {
    "type" : "Feature",
    "geometry" : {
      "type" : "Point",
      "coordinates" : [ -71.1114458017, 42.3754311174 ]
    },
    "properties" : {
      "type" : "place",
      "startTime" : "20140916T221733-0400",
      "endTime" : "20140917T065440-0400",
      "place" : {
        "id" : 9869005,
        "name" : "Home",
        "type" : "home",
        "location" : {
          "lat" : 42.3754311174,
          "lon" : -71.1114458017
        }
      },
      "lastUpdate" : "20140917T121756Z",
      "date" : "20140917"
    }
  }, {
    "type" : "Feature",
    "geometry" : {
      "type" : "Point",
      "coordinates" : [ -71.12407621183526, 42.36403242532342 ]
    },
    "properties" : {
      "type" : "place",
      "startTime" : "20140917T072129-0400",
      "endTime" : "20140917T085329-0400",
      "place" : {
        "id" : 11237847,
        "name" : "Harvard Innovation Lab",
        "type" : "foursquare",
        "foursquareId" : "4e5d4676ae60839ea2e29e64",
        "foursquareCategoryIds" : [ "4bf58dd8d48988d19f941735" ],
        "location" : {
          "lat" : 42.36403242532342,
          "lon" : -71.12407621183526
        }
      },
      "lastUpdate" : "20140917T135105Z",
      "date" : "20140917"
    }
  }, {
    "type" : "Feature",
    "geometry" : {
      "type" : "Point",
      "coordinates" : [ -71.12210915179602, 42.36578780710847 ]
    },
    "properties" : {
      "type" : "place",
      "startTime" : "20140917T090058-0400",
      "endTime" : "20140917T145003-0400",
      "place" : {
        "id" : 84119446,
        "name" : "Aldrich Hall",
        "type" : "foursquare",
        "foursquareId" : "4ac64359f964a5206eb320e3",
        "foursquareCategoryIds" : [ "4bf58dd8d48988d198941735" ],
        "location" : {
          "lat" : 42.36578780710847,
          "lon" : -71.12210915179602
        }
      },
      "lastUpdate" : "20141008T024703Z",
      "date" : "20140917"
    }
  }, {
    "type" : "Feature",
    "geometry" : {
      "type" : "Point",
      "coordinates" : [ -71.1114458017, 42.3754311174 ]
    },
    "properties" : {
      "type" : "place",
      "startTime" : "20140917T161809-0400",
      "endTime" : "20140917T185930-0400",
      "place" : {
        "id" : 9869005,
        "name" : "Home",
        "type" : "home",
        "location" : {
          "lat" : 42.3754311174,
          "lon" : -71.1114458017
        }
      },
      "lastUpdate" : "20140918T003703Z",
      "date" : "20140917"
    }
  }, {
    "type" : "Feature",
    "geometry" : {
      "type" : "Point",
      "coordinates" : [ -71.120141, 42.3743468 ]
    },
    "properties" : {
      "type" : "place",
      "startTime" : "20140917T191006-0400",
      "endTime" : "20140917T200637-0400",
      "place" : {
        "id" : 10042715,
        "name" : "Border Cafe",
        "type" : "foursquare",
        "foursquareId" : "3fd66200f964a520bded1ee3",
        "foursquareCategoryIds" : [ "4bf58dd8d48988d1c1941735", "4bf58dd8d48988d17a941735" ],
        "location" : {
          "lat" : 42.3743468,
          "lon" : -71.120141
        }
      },
      "lastUpdate" : "20140922T170440Z",
      "date" : "20140917"
    }
  }, {
    "type" : "Feature",
    "geometry" : {
      "type" : "Point",
      "coordinates" : [ -71.1114458017, 42.3754311174 ]
    },
    "properties" : {
      "type" : "place",
      "startTime" : "20140917T202247-0400",
      "endTime" : "20140918T072615-0400",
      "place" : {
        "id" : 9869005,
        "name" : "Home",
        "type" : "home",
        "location" : {
          "lat" : 42.3754311174,
          "lon" : -71.1114458017
        }
      },
      "lastUpdate" : "20140918T124656Z",
      "date" : "20140917"
    }
  } ]
}