{
  "type" : "FeatureCollection",
  "features" : [ {
    "type" : "Feature",
    "geometry" : {
      "type" : "Point",
      "coordinates" : [ -71.1114458017, 42.3754311174 ]
    },
    "properties" : {
      "type" : "place",
      "startTime" : "20140909T174215-0500",
      "endTime" : "20140910T085618-0500",
      "place" : {
        "id" : 9869005,
        "name" : "Home",
        "type" : "home",
        "location" : {
          "lat" : 42.3754311174,
          "lon" : -71.1114458017
        }
      },
      "lastUpdate" : "20140910T154724Z",
      "date" : "20140910"
    }
  }, {
    "type" : "Feature",
    "geometry" : {
      "type" : "Point",
      "coordinates" : [ -71.12218458495514, 42.36522543920124 ]
    },
    "properties" : {
      "type" : "place",
      "startTime" : "20140910T091954-0500",
      "endTime" : "20140910T161619-0500",
      "place" : {
        "id" : 10115332,
        "name" : "Spangler Center",
        "type" : "foursquare",
        "foursquareId" : "4aeee0b0f964a52081d421e3",
        "foursquareCategoryIds" : [ "4bf58dd8d48988d1ab941735" ],
        "location" : {
          "lat" : 42.36522543920124,
          "lon" : -71.12218458495514
        }
      },
      "lastUpdate" : "20141129T021506Z",
      "date" : "20140910"
    }
  }, {
    "type" : "Feature",
    "geometry" : {
      "type" : "Point",
      "coordinates" : [ -71.1114458017, 42.3754311174 ]
    },
    "properties" : {
      "type" : "place",
      "startTime" : "20140910T164045-0500",
      "endTime" : "20140910T205913-0500",
      "place" : {
        "id" : 9869005,
        "name" : "Home",
        "type" : "home",
        "location" : {
          "lat" : 42.3754311174,
          "lon" : -71.1114458017
        }
      },
      "lastUpdate" : "20140911T054908Z",
      "date" : "20140910"
    }
  }, {
    "type" : "Feature",
    "geometry" : {
      "type" : "Point",
      "coordinates" : [ -71.1114357056, 42.3700145918 ]
    },
    "properties" : {
      "type" : "place",
      "startTime" : "20140910T210753-0500",
      "endTime" : "20140910T212055-0500",
      "place" : {
        "id" : 92217670,
        "name" : "Will Whitney and Benjana Guraziu Home",
        "type" : "home",
        "location" : {
          "lat" : 42.3700145918,
          "lon" : -71.1114357056
        }
      },
      "lastUpdate" : "20140911T110052Z",
      "date" : "20140910"
    }
  }, {
    "type" : "Feature",
    "geometry" : {
      "type" : "Point",
      "coordinates" : [ -71.06571601465738, 42.35241910162504 ]
    },
    "properties" : {
      "type" : "place",
      "startTime" : "20140910T214237-0500",
      "endTime" : "20140910T224321-0500",
      "place" : {
        "id" : 92155067,
        "name" : "Whisky Saigon",
        "type" : "foursquare",
        "foursquareId" : "5279339111d23f7e3e40c260",
        "foursquareCategoryIds" : [ "4bf58dd8d48988d11f941735" ],
        "location" : {
          "lat" : 42.35241910162504,
          "lon" : -71.06571601465738
        }
      },
      "lastUpdate" : "20140911T110019Z",
      "date" : "20140910"
    }
  }, {
    "type" : "Feature",
    "geometry" : {
      "type" : "Point",
      "coordinates" : [ -71.1114458017, 42.3754311174 ]
    },
    "properties" : {
      "type" : "place",
      "startTime" : "20140910T230850-0500",
      "endTime" : "20140911T063026-0500",
      "place" : {
        "id" : 9869005,
        "name" : "Home",
        "type" : "home",
        "location" : {
          "lat" : 42.3754311174,
          "lon" : -71.1114458017
        }
      },
      "lastUpdate" : "20140911T153859Z",
      "date" : "20140910"
    }
  } ]
}