{
  "type" : "FeatureCollection",
  "features" : [ {
    "type" : "Feature",
    "geometry" : {
      "type" : "Point",
      "coordinates" : [ -71.1114458017, 42.3754311174 ]
    },
    "properties" : {
      "type" : "place",
      "startTime" : "20140913T153806-0500",
      "endTime" : "20140914T120342-0500",
      "place" : {
        "id" : 9869005,
        "name" : "Home",
        "type" : "home",
        "location" : {
          "lat" : 42.3754311174,
          "lon" : -71.1114458017
        }
      },
      "lastUpdate" : "20140914T181623Z",
      "date" : "20140914"
    }
  }, {
    "type" : "Feature",
    "geometry" : {
      "type" : "Point",
      "coordinates" : [ -71.119043, 42.373776 ]
    },
    "properties" : {
      "type" : "place",
      "startTime" : "20140914T121826-0500",
      "endTime" : "20140914T122440-0500",
      "place" : {
        "id" : 94226569,
        "name" : "Staples",
        "type" : "foursquare",
        "foursquareId" : "4b1e88eaf964a520321b24e3",
        "foursquareCategoryIds" : [ "4bf58dd8d48988d121951735" ],
        "location" : {
          "lat" : 42.373776,
          "lon" : -71.119043
        }
      },
      "lastUpdate" : "20141217T041854Z",
      "date" : "20140914"
    }
  }, {
    "type" : "Feature",
    "geometry" : {
      "type" : "Point",
      "coordinates" : [ -71.11655026913272, 42.3717166982379 ]
    },
    "properties" : {
      "type" : "place",
      "startTime" : "20140914T123052-0500",
      "endTime" : "20140914T123319-0500",
      "place" : {
        "id" : 94226617,
        "name" : "Adams House",
        "type" : "foursquare",
        "foursquareId" : "4b5e4514f964a520f28629e3",
        "foursquareCategoryIds" : [ "4bf58dd8d48988d1a3941735" ],
        "location" : {
          "lat" : 42.3717166982379,
          "lon" : -71.11655026913272
        }
      },
      "lastUpdate" : "20140917T023934Z",
      "date" : "20140914"
    }
  }, {
    "type" : "Feature",
    "geometry" : {
      "type" : "Point",
      "coordinates" : [ -71.1114458017, 42.3754311174 ]
    },
    "properties" : {
      "type" : "place",
      "startTime" : "20140914T124521-0500",
      "endTime" : "20140915T062606-0500",
      "place" : {
        "id" : 9869005,
        "name" : "Home",
        "type" : "home",
        "location" : {
          "lat" : 42.3754311174,
          "lon" : -71.1114458017
        }
      },
      "lastUpdate" : "20140915T125411Z",
      "date" : "20140914"
    }
  } ]
}